{
  "1": {
    "hypersdn": {
      "label": "v-0001262-4880a9dd",
      "promotedTime": "2018-10-10T03:50:43.710603377Z"
    },
    "slbnginx": {
      "label": "v-0000040-632d2743",
      "promotedTime": "2018-09-05T22:22:37.686673087Z"
    }
  },
  "2": {
    "hypersdn": {
      "label": "v-0001262-4880a9dd",
      "promotedTime": "2018-10-10T05:21:18.341823831Z"
    },
    "slbnginx": {
      "label": "v-0000040-632d2743",
      "promotedTime": "2018-09-06T05:45:53.410312825Z"
    }
  },
  "3": {
    "hypersdn": {
      "label": "v-0001262-4880a9dd",
      "promotedTime": "2018-10-10T15:21:11.981964091Z"
    },
    "slbnginx": {
      "label": "v-0000040-632d2743",
      "promotedTime": "2018-09-06T19:35:12.412763674Z"
    }
  },
  "4": {
    "hypersdn": {
      "label": "v-0001261-c2aa8b39",
      "promotedTime": "2018-10-10T05:21:18.341793657Z"
    },
    "slbnginx": {
      "label": "v-0000040-632d2743",
      "promotedTime": "2018-09-06T20:56:04.27206933Z"
    }
  }
}