{
  "1": {
    "hypersdn": {
      "label": "v-0001431-8e59833f",
      "promotedTime": "2019-01-16T20:16:33.44529769Z"
    },
    "kmsnginx": {
      "label": "v-0000060-cefcf926",
      "promotedTime": "2019-01-16T19:36:15.857904709Z"
    },
    "slbnginx": {
      "label": "v-0000060-cefcf926",
      "promotedTime": "2019-01-16T19:39:45.614037763Z"
    }
  },
  "2": {
    "hypersdn": {
      "label": "v-0001431-8e59833f",
      "promotedTime": "2019-01-17T00:31:16.78958204Z"
    },
    "kmsnginx": {
      "label": "v-0000058-f078c862",
      "promotedTime": "2019-01-04T19:59:10.830395885Z"
    },
    "slbnginx": {
      "label": "v-0000058-f078c862",
      "promotedTime": "2019-01-03T16:35:50.112529962Z"
    }
  },
  "3": {
    "hypersdn": {
      "label": "v-0001425-bead11cd",
      "promotedTime": "2019-01-17T00:31:16.789553864Z"
    },
    "kmsnginx": {
      "label": "v-0000058-f078c862",
      "promotedTime": "2019-01-04T21:28:23.515182245Z"
    },
    "slbnginx": {
      "label": "v-0000058-f078c862",
      "promotedTime": "2019-01-04T15:38:37.626715214Z"
    }
  },
  "4": {
    "hypersdn": {
      "label": "v-0001423-9a396d66",
      "promotedTime": "2019-01-15T18:30:27.585155136Z"
    },
    "kmsnginx": {
      "label": "v-0000058-f078c862",
      "promotedTime": "2019-01-04T23:28:23.135809177Z"
    },
    "slbnginx": {
      "label": "v-0000058-f078c862",
      "promotedTime": "2019-01-04T17:39:52.781427556Z"
    }
  },
  "5": {
    "hypersdn": {
      "label": "v-0001423-9a396d66",
      "promotedTime": "2019-01-17T00:31:16.789512477Z"
    },
    "kmsnginx": {
      "label": "v-0000058-f078c862",
      "promotedTime": "2019-01-05T01:28:31.665826009Z"
    },
    "slbnginx": {
      "label": "v-0000058-f078c862",
      "promotedTime": "2019-01-04T19:04:40.541202361Z"
    }
  }
}