{
  "1": {
    "k4acaimanwatchdog": {
      "label": "208-3df07eeaa89d0025c5a39ee629ffb0f20ee02553",
      "promotedTime": "2019-12-06T16:38:07.632714294Z"
    },
    "sswatchdog": {
      "label": "191-4acd4ee582db728abe2631b5fd9b0161e5b2ebed",
      "promotedTime": "2019-11-26T08:42:39.984221016Z"
    }
  },
  "2": {
    "k4acaimanwatchdog": {
      "label": "203-2c639c53fbe71c0348669883ba3c510f1d86c8ab",
      "promotedTime": "2019-11-28T01:06:26.121074354Z"
    },
    "sswatchdog": {
      "label": "191-4acd4ee582db728abe2631b5fd9b0161e5b2ebed",
      "promotedTime": "2019-12-06T18:44:55.324677435Z"
    }
  },
  "3": {
    "k4acaimanwatchdog": {
      "label": "203-2c639c53fbe71c0348669883ba3c510f1d86c8ab",
      "promotedTime": "2019-11-28T02:23:13.314207524Z"
    },
    "sswatchdog": {
      "label": "180-195c512830ddab15bfe81627852dfa09cbeb641f",
      "promotedTime": "2019-12-06T18:44:55.324653947Z"
    }
  },
  "4": {
    "k4acaimanwatchdog": {
      "label": "202-e32fac4466fdc303a83a7743e951377ef4ca0616",
      "promotedTime": "2019-11-25T19:45:10.239999723Z"
    },
    "sswatchdog": {
      "label": "177-32163c58278bc26ebee8466939c336906c0a3c6e",
      "promotedTime": "2019-12-06T18:44:55.3246236Z"
    }
  }
}